<?xml version="1.0" encoding="utf-8"?>
<Database xmlns:xsd="http://www.w3.org/2001/XMLSchema" xmlns:xsi="http://www.w3.org/2001/XMLSchema-instance" Name="brambora">
	<Skald>
		<Module Name="streaming__trosky_settling" HasteNamespace="true" Purpose="LocationControl">
			<Ports>
				<Port Name="osazeni__otevreny_hrad" Direction="In" Type="trigger">
					<DesignName StringName="streaming_stream_soldiers_WEft" Text="Osazení - otevřený hrad" />
				</Port>
				<Port Name="osazeni__pocas_m09_utok_na_nebakov" Direction="In" Type="trigger">
					<DesignName StringName="streaming_stream_m09_IY9B" Text="Osazení - počas M09 Útok na Nebákov" />
				</Port>
				<Port Name="osazeni__pocas_m09_utok_na_nebakov_rano" Direction="In" Type="trigger">
					<DesignName StringName="streaming_osazeni__pocas__SLZO" Text="Osazení - počas M09 Útok na Nebákov ráno" />
				</Port>
				<Port Name="osazeni__pocas_m12_vezni_na_troskach" Direction="In" Type="trigger">
					<DesignName StringName="streaming_settling_during_TlHc" Text="Osazení - počas M12 Vězni na Troskách" />
				</Port>
				<Port Name="osazeni__po_m12_vezni_na_troskach" Direction="In" Type="trigger">
					<DesignName StringName="streaming_osazeni__po_m12_63oX" Text="Osazení - po M12 Vězni na Troskách" />
				</Port>
			</Ports>
			<Nodes>
				<MakeArray Name="makearray12" PositionY="490" PositionX="-970" TypeT="wh::conceptmodule::ConceptPaths">
					<Constant Name="A" Value="tomas_hejtman.stream" />
				</MakeArray>
				<MakeArray Name="makearray12_1" PositionY="890" PositionX="-970" TypeT="wh::conceptmodule::ConceptPaths">
					<Constant Name="A" Value="tomas_hejtman.troskyOwner" />
				</MakeArray>
				<Function Name="or5" PositionY="-290" PositionX="520" MethodName="math::boolean::Or" DeclaringType="math::boolean">
					<Edge From="troskySettlingState.DefaultSettling_CastleOpen" To="A" />
					<Edge From="troskySettlingState.SettlingAfterVezniNaTroskach" To="B" />
					<Edge From="troskySettlingState.SettlingDuringUtokNaNebakovMorning" To="C" />
				</Function>
				<Function Name="or7" PositionY="-110" PositionX="520" MethodName="math::boolean::Or" DeclaringType="math::boolean">
					<Edge From="troskySettlingState.DefaultSettling_CastleOpen" To="A" />
					<Edge From="troskySettlingState.SettlingDuringVezniNaTroskach" To="B" />
				</Function>
				<Function Name="or8" PositionY="40" PositionX="520" MethodName="math::boolean::Or" DeclaringType="math::boolean">
					<Edge From="troskySettlingState.SettlingDuringUtokNaNebakov" To="A" />
					<Edge From="troskySettlingState.SettlingDuringUtokNaNebakovMorning" To="B" />
				</Function>
				<Layer Name="profile11" PositionY="470" PositionX="950">
					<Asset Name="Profiles" Alias="trosky_gossipAreas" />
					<Edge From="switch10.Value1" To="IsActive" />
				</Layer>
				<Layer Name="profile3" PositionY="-290" PositionX="790">
					<Asset Name="Profiles" Alias="trosky_defaultSettling" />
					<Edge From="or5.bool" To="IsActive" />
				</Layer>
				<Layer Name="profile3_1" PositionY="10" PositionX="790">
					<Asset Name="Profiles" Alias="trosky_M09settling" />
					<Edge From="or8.bool" To="IsActive" />
				</Layer>
				<Layer Name="profile4" PositionY="210" PositionX="790">
					<Asset Name="Profiles" Alias="trosky_kroupaReplacement" />
					<Edge From="troskySettlingState.SettlingAfterVezniNaTroskach" To="IsActive" />
				</Layer>
				<Layer Name="profile4_1" PositionY="-470" PositionX="520">
					<Asset Name="Profiles" Alias="trosky_vykuchHradi" />
					<Edge From="troskySettlingState.AllNpcsUnstreamed_CastleClosed" To="IsActive" />
				</Layer>
				<Layer Name="profile6" PositionY="-140" PositionX="790">
					<Asset Name="Profiles" Alias="trosky_kroupa" />
					<Edge From="or7.bool" To="IsActive" />
				</Layer>
				<HasteTrigger Name="settlingDuringClosedCastle" PositionY="-610" PositionX="-670">
					<Constant Name="IsHidden" Value="true" />
				</HasteTrigger>
				<HasteTrigger Name="settlingDuringOpenedCastle" PositionY="-380" PositionX="-670">
					<Constant Name="IsHidden" Value="true" />
					<Edge From="makearray12.Array" To="Prerequisites" />
				</HasteTrigger>
				<Switch Name="switch10" PositionY="470" PositionX="490" TypeT="troskySettling" ValueTypes="bool" SwitchValues="DefaultSettling_CastleOpen SettlingDuringUtokNaNebakov SettlingDuringUtokNaNebakovMorning SettlingAfterVezniNaTroskach">
					<Constant Name="DefaultSettling_CastleOpenValue1" Value="true" />
					<Constant Name="SettlingDuringUtokNaNebakovValue1" Value="true" />
					<Constant Name="SettlingDuringUtokNaNebakovMorningValue1" Value="true" />
					<Constant Name="SettlingAfterVezniNaTroskachValue1" Value="true" />
					<Constant Name="DefaultValue1" Value="false" />
					<Edge From="troskySettlingState.State" To="Switch" />
				</Switch>
				<HasteTrigger Name="troskyNpcs_duringAfterVezniNaTroskach" PositionY="790" PositionX="-640">
					<Constant Name="IsHidden" Value="true" />
					<Edge From="makearray12_1.Array" To="Prerequisites" />
				</HasteTrigger>
				<HasteTrigger Name="troskyNpcs_duringM09" PositionY="350" PositionX="-640">
					<Constant Name="IsHidden" Value="true" />
					<Edge From="makearray12.Array" To="Prerequisites" />
				</HasteTrigger>
				<HasteTrigger Name="troskyNpcs_duringVezniNaTroskach" PositionY="570" PositionX="-640">
					<Constant Name="IsHidden" Value="true" />
					<Edge From="makearray12_1.Array" To="Prerequisites" />
				</HasteTrigger>
				<State Name="troskySettlingState" PositionY="-210" PositionX="-260" TypeT="troskySettling">
					<Constant Name="DefaultValue" Value="AllNpcsUnstreamed_CastleClosed" />
					<Edge From="osazeni__pocas_m09_utok_na_nebakov" To="SetSettlingDuringUtokNaNebakov" />
					<Edge From="osazeni__pocas_m12_vezni_na_troskach" To="SetSettlingDuringVezniNaTroskach" />
					<Edge From="troskyNpcs_duringM09.OnTrigger" To="SetSettlingDuringUtokNaNebakov" />
					<Edge From="osazeni__po_m12_vezni_na_troskach" To="SetSettlingAfterVezniNaTroskach" />
					<Edge From="osazeni__otevreny_hrad" To="SetDefaultSettling_CastleOpen" />
					<Edge From="settlingDuringClosedCastle.OnTrigger" To="SetAllNpcsUnstreamed_CastleClosed" />
					<Edge From="settlingDuringOpenedCastle.OnTrigger" To="SetDefaultSettling_CastleOpen" />
					<Edge From="osazeni__pocas_m09_utok_na_nebakov_rano" To="SetSettlingDuringUtokNaNebakovMorning" />
					<Edge From="troskyNpcs_duringAfterVezniNaTroskach.OnTrigger" To="SetSettlingAfterVezniNaTroskach" />
					<Edge From="troskyNpcs_duringVezniNaTroskach.OnTrigger" To="SetSettlingDuringVezniNaTroskach" />
				</State>
			</Nodes>
			<Types>
				<Type TypeName="troskySettling">
					<StateTypeEnumeration Name="AllNpcsUnstreamed_CastleClosed" ObjectiveValueType="None" />
					<StateTypeEnumeration Name="DefaultSettling_CastleOpen" ObjectiveValueType="None" />
					<StateTypeEnumeration Name="SettlingDuringUtokNaNebakov" ObjectiveValueType="None" />
					<StateTypeEnumeration Name="SettlingDuringUtokNaNebakovMorning" ObjectiveValueType="None" />
					<StateTypeEnumeration Name="SettlingDuringVezniNaTroskach" ObjectiveValueType="None" />
					<StateTypeEnumeration Name="SettlingAfterVezniNaTroskach" ObjectiveValueType="None" />
				</Type>
			</Types>
			<Assets>
				<ProfileAsset Name="trosky_defaultSettling" AssetProfiles="trosky_settlingDefault" />
				<ProfileAsset Name="trosky_M09settling" AssetProfiles="trosky_settlingM09" />
				<ProfileAsset Name="trosky_kroupaReplacement" AssetProfiles="trosky_kroupaReplacement" />
				<ProfileAsset Name="trosky_kroupa" AssetProfiles="trosky_kroupa" />
				<ProfileAsset Name="trosky_vykuchHradi" AssetProfiles="ttro_closedCastle_vykuchHrad" />
				<ProfileAsset Name="trosky_gossipAreas" AssetProfiles="trosky_gossipAreas" />
			</Assets>
			<Text StringName="streaming__trosky_soldiers_XnU3" Text="Streaming - Trosky settling" />
		</Module>
	</Skald>
</Database>