<?xml version="1.0" encoding="utf-8"?>
<Database xmlns:xsd="http://www.w3.org/2001/XMLSchema" xmlns:xsi="http://www.w3.org/2001/XMLSchema-instance" Name="brambora">
	<Skald>
		<Module Name="vezicko" Purpose="LocationControl">
			<Ports>
				<Port Name="quest_progress" Direction="In" Type="wh::questmodule::QuestProgress">
					<DesignName StringName="vezicko_quest_progress_gtyn" Text="M01 Přepadení" />
				</Port>
				<Port Name="vyuka_sermu_bezi" Direction="In" Type="bool">
					<DesignName StringName="vezicko_vyuka_sermu_bezi_z2HK" Text="výuka šermu běží" />
				</Port>
			</Ports>
			<Definitions>
				<Definition File="vezicko/cesty_v_ptackove_kempu.xml" />
				<Definition File="vezicko/caponsCamp_ledgeBarrierHandler.xml" />
			</Definitions>
			<Nodes>
				<caponsCamp_ledgeBarrierHandler Name="caponsCamp_ledgeBarrierHandler" PositionY="-90" PositionX="-10">
					<Edge From="vyuka_sermu_bezi" To="vyuka_sermu_bezi" />
				</caponsCamp_ledgeBarrierHandler>
				<cesty_v_ptackove_kempu Name="cesty_v_ptackove_kempu" PositionY="-240" PositionX="-10">
					<Edge From="quest_progress" To="quest_progress" />
				</cesty_v_ptackove_kempu>
			</Nodes>
			<Text StringName="vezicko_5w5y" Text="Vežicko" />
		</Module>
	</Skald>
</Database>