<?xml version="1.0" encoding="us-ascii"?>
<BehaviorTrees>
	<BehaviorTree name="stealth_recognitionState_I_reaction" is_function="1">
		<Variables>
			<Variable name="schedulerPriority" type="_int" values="" isPersistent="0" form="single" />
		</Variables>
		<Parameters>
			<Variable name="target" type="_wuid" values="" isPersistent="0" form="single" requirementType="In" />
		</Parameters>
		<Root OneTimeOnly="false" FailState="Recoverable" saveVersion="2">
			<Behavior canSkip="1">
				<Sequence>
					<IfCondition failOnCondition="false" condition="$target == $__player">
						<EntityContextCheck context="crime_interruptWatch" target="" saveVersion="2">
							<Else canSkip="1">
								<EntityContextCheck context="crime_interruptMindPlayer" target="" saveVersion="2">
									<Else canSkip="1">
										<EntityContextCheck context="crime_interruptReport" target="" saveVersion="2">
											<Else canSkip="1">
												<EntityContextCheck context="crime_interruptMercy" target="" saveVersion="2">
													<Else canSkip="1">
														<EntityContextCheck context="crime_interruptFlee" target="" saveVersion="2">
															<Else canSkip="1">
																<EntityContextCheck context="switch_doNotOpenRecognizingLock" target="" saveVersion="2">
																	<Else canSkip="1">
																		<SetExternalLock LockManagerType="Intellect" Locked="false" LockName="&apos;crime_escalationLevel_recognizing&apos;" />
																	</Else>
																</EntityContextCheck>
															</Else>
														</EntityContextCheck>
													</Else>
												</EntityContextCheck>
											</Else>
										</EntityContextCheck>
									</Else>
								</EntityContextCheck>
							</Else>
						</EntityContextCheck>
					</IfCondition>
					<DistanceCondition Origin="$this.id" ReferencePt="$target" Low="5.000000" High="5.000000" Negation="true" ValueOnMiddle="false" failOnCondition="false">
						<Sequence>
							<GetScheduledPriority Priority="$schedulerPriority" />
							<IfCondition failOnCondition="false" condition="$schedulerPriority &lt;= 29">
								<Sequence>
									<EntityContextCheck context="movingFar" target="" saveVersion="2">
										<Then canSkip="1">
											<PlayAdditiveAnimation Fragment="&apos;GuardRecognition&apos;" Tags="" />
										</Then>
									</EntityContextCheck>
									<Function_crime_crimeSwitchBark animationApproach="$enum:animationApproach.dontPlayDialogAnimations" canBarkFromSleep="false" canBeDelayed="false" dialogContext="" dramaticBark="false" lookAt="$target" metarole="&apos;NPC_REAGUJE_NA_STAV_I_(UNIVERZAL)&apos;" priority="$enum:crime_barkPriority.medium" nodeLabel="82352549" />
								</Sequence>
							</IfCondition>
						</Sequence>
					</DistanceCondition>
				</Sequence>
			</Behavior>
		</Root>
		<ForestContainer />
		<EditorData EventSet="">
			<Variables>
				<Variable name="schedulerPriority" comment="" />
				<Variable name="target" comment="" />
			</Variables>
			<ForwardDeclarations />
			<Root hasInputBreakpoint="0" comment="" breakpointFlags="0" saveVersion="2">
				<OutputBreakpoints />
				<Behavior>
					<Sequence hasInputBreakpoint="0" comment="" breakpointFlags="0">
						<OutputBreakpoints />
						<IfCondition hasInputBreakpoint="0" comment="" breakpointFlags="0">
							<OutputBreakpoints />
							<EntityContextCheck hasInputBreakpoint="0" comment="KCD2-340372" breakpointFlags="0" saveVersion="2">
								<OutputBreakpoints />
								<Else>
									<EntityContextCheck hasInputBreakpoint="0" comment="KCD2-360221" breakpointFlags="0" saveVersion="2">
										<OutputBreakpoints />
										<Else>
											<EntityContextCheck hasInputBreakpoint="0" comment="KCD2-360221" breakpointFlags="0" saveVersion="2">
												<OutputBreakpoints />
												<Else>
													<EntityContextCheck hasInputBreakpoint="0" comment="KCD2-422955" breakpointFlags="0" saveVersion="2">
														<OutputBreakpoints />
														<Else>
															<EntityContextCheck hasInputBreakpoint="0" comment="KCD2-422955" breakpointFlags="0" saveVersion="2">
																<OutputBreakpoints />
																<Else>
																	<EntityContextCheck hasInputBreakpoint="0" comment="KCD2-429445" breakpointFlags="0" saveVersion="2">
																		<OutputBreakpoints />
																		<Else>
																			<SetExternalLock hasInputBreakpoint="0" comment="" breakpointFlags="0">
																				<OutputBreakpoints />
																			</SetExternalLock>
																		</Else>
																	</EntityContextCheck>
																</Else>
															</EntityContextCheck>
														</Else>
													</EntityContextCheck>
												</Else>
											</EntityContextCheck>
										</Else>
									</EntityContextCheck>
								</Else>
							</EntityContextCheck>
						</IfCondition>
						<DistanceCondition hasInputBreakpoint="0" comment="" breakpointFlags="0">
							<OutputBreakpoints />
							<Sequence hasInputBreakpoint="0" comment="" breakpointFlags="0">
								<OutputBreakpoints />
								<GetScheduledPriority hasInputBreakpoint="0" comment="" breakpointFlags="0">
									<OutputBreakpoints />
								</GetScheduledPriority>
								<IfCondition hasInputBreakpoint="0" comment="TODO: number" breakpointFlags="0">
									<OutputBreakpoints />
									<Sequence hasInputBreakpoint="0" comment="" breakpointFlags="0">
										<OutputBreakpoints />
										<EntityContextCheck hasInputBreakpoint="0" comment="" breakpointFlags="0" saveVersion="2">
											<OutputBreakpoints />
											<Then>
												<PlayAdditiveAnimation hasInputBreakpoint="0" comment="" breakpointFlags="0">
													<OutputBreakpoints />
												</PlayAdditiveAnimation>
											</Then>
										</EntityContextCheck>
										<Function_crime_crimeSwitchBark hasInputBreakpoint="0" comment="" breakpointFlags="0">
											<OutputBreakpoints />
										</Function_crime_crimeSwitchBark>
									</Sequence>
								</IfCondition>
							</Sequence>
						</DistanceCondition>
					</Sequence>
				</Behavior>
			</Root>
			<Forest />
			<Comments />
		</EditorData>
	</BehaviorTree>
</BehaviorTrees>