<?xml version="1.0" encoding="utf-8"?>
<Database xmlns:xsd="http://www.w3.org/2001/XMLSchema" xmlns:xsi="http://www.w3.org/2001/XMLSchema-instance" Name="brambora">
	<Skald>
		<Module Name="soldierorplayerinarea">
			<Ports>
				<Port Name="somebodyinside" Direction="Out" Type="bool">
					<DesignName StringName="soldieror_inside_kYtv" Text="SomebodyInside" />
				</Port>
				<Port Name="area" Direction="In" Type="wh::xgenaimodule::Areas">
					<DesignName StringName="soldieror_area_ZzSw" Text="Area" />
				</Port>
			</Ports>
			<Nodes>
				<Function Name="areacheck1" PositionY="-360" PositionX="-30" MethodName="wh::rpgmodule::AreaCheck" DeclaringType="wh::rpgmodule">
					<Asset Name="Souls" Alias="player" />
					<Edge From="area" To="Areas" />
				</Function>
				<Function Name="areacheck1_1" PositionY="-60" PositionX="-30" MethodName="wh::rpgmodule::AreaCheck" DeclaringType="wh::rpgmodule">
					<Asset Name="Souls" Alias="cuman2" />
					<Edge From="area" To="Areas" />
				</Function>
				<Function Name="areacheck3" PositionY="-210" PositionX="-30" MethodName="wh::rpgmodule::AreaCheck" DeclaringType="wh::rpgmodule">
					<Asset Name="Souls" Alias="cuman1" />
					<Edge From="area" To="Areas" />
				</Function>
				<Function Name="areacheck3_1" PositionY="90" PositionX="-30" MethodName="wh::rpgmodule::AreaCheck" DeclaringType="wh::rpgmodule">
					<Asset Name="Souls" Alias="cuman3" />
					<Edge From="area" To="Areas" />
				</Function>
				<Function Name="areacheck4" PositionY="240" PositionX="-50" MethodName="wh::rpgmodule::AreaCheck" DeclaringType="wh::rpgmodule">
					<Asset Name="Souls" Alias="commander" />
					<Edge From="area" To="Areas" />
				</Function>
				<Function Name="or5" PositionY="-130" PositionX="290" MethodName="math::boolean::Or" DeclaringType="math::boolean">
					<Edge From="areacheck1.IsInside" To="A" />
					<Edge From="areacheck3.IsInside" To="B" />
					<Edge From="areacheck1_1.IsInside" To="C" />
					<Edge From="areacheck3_1.IsInside" To="D" />
					<Edge From="areacheck4.IsInside" To="E" />
				</Function>
				<Output Name="Output">
					<Edge From="or5.bool" To="somebodyinside" />
				</Output>
			</Nodes>
			<Text StringName="soldierorplayerinarea_v8ny" Text="SoldierOrPlayerInArea" />
		</Module>
	</Skald>
</Database>