<?xml version="1.0" encoding="utf-8"?>
<Database xmlns:xsd="http://www.w3.org/2001/XMLSchema" xmlns:xsi="http://www.w3.org/2001/XMLSchema-instance" Name="brambora">
	<Skald>
		<Gameplay Name="kradez_knihy__pisar">
			<Ports>
				<Port Name="svatba_done" Direction="In" Type="trigger">
					<DesignName StringName="kradez_kn_svatba_done_tjHF" Text="Svatba done" />
				</Port>
				<Port Name="akteri_odhaleni" Direction="Out" Type="trigger">
					<DesignName StringName="kradez_kn_knihumakucharka_xXfu" Text="Aktéři odhaleni" />
				</Port>
				<Port Name="itemy_do_inventare" Direction="Out" Type="bool">
					<DesignName StringName="kradez_kn_kucharku_do_bed_JXA5" Text="itemy do inventáře" />
				</Port>
				<Port Name="hrac_nasel_knihu_exec" Direction="In" Type="trigger">
					<DesignName StringName="kradez_kn_hrac_nasel_knih_37md" Text="abort" />
				</Port>
				<Port Name="lokace_kucharky" Direction="Out" Type="trigger">
					<DesignName StringName="kradez_kn_lokace_kucharky_scQF" Text="Lokace kuchařky" />
				</Port>
				<Port Name="lokace_pacholka" Direction="Out" Type="trigger">
					<DesignName StringName="kradez_kn_lokace_pacholka_Ik08" Text="Lokace pacholka" />
				</Port>
				<Port Name="lokace_sluzky" Direction="Out" Type="trigger">
					<DesignName StringName="kradez_kn_lokace_sluzky_TA5V" Text="Lokace služky" />
				</Port>
				<Port Name="vim_proc_nik_potreboval_lek" Direction="In" Type="bool">
					<DesignName StringName="kradez_kn_vim_proc_nik_po_GUZp" Text="Vím proč Nik potřeboval lék" />
				</Port>
				<Port Name="mluvil_jsem_s_kucharkou" Direction="In" Type="bool">
					<DesignName StringName="kradez_kn_mluvil_jsem_s_k_gROu" Text="Mluvil jsem s kuchařkou" />
				</Port>
				<Port Name="mluvil_jsem_se_sluzkou" Direction="In" Type="bool">
					<DesignName StringName="kradez_kn_mluvil_jsem_se__yV5R" Text="Mluvil jsem se služkou" />
				</Port>
				<Port Name="vim_co_se_pise_v_dopise" Direction="In" Type="bool">
					<DesignName StringName="kradez_kn_vim_co_se_pise__fCt1" Text="Vím co se píše v dopise" />
				</Port>
				<Port Name="mluvil_jsem_s_pacholkem" Direction="In" Type="bool">
					<DesignName StringName="kradez_kn_mluvil_jsem_s_p_HsbF" Text="Mluvil jsem s pacholkem" />
				</Port>
				<Port Name="vim_co_chtel_nik_po_pacholkovi" Direction="In" Type="bool">
					<DesignName StringName="kradez_kn_vim_co_chtel_ni_wSIY" Text="Vím co chtěl Nik po pacholkovi" />
				</Port>
				<Port Name="m06_active" Direction="In" Type="bool">
					<DesignName StringName="kradez_kn_m06_active_BOzz" Text="M06 active" />
				</Port>
				<Port Name="misto_nikvardova_posledniho_odpocinku" Direction="Out" Type="trigger">
					<DesignName StringName="kradez_kn_misto_nikvardov_tJiN" Text="Místo Nikvardova posledního odpočinku" />
				</Port>
				<Port Name="promluvil_jsem_s_pisarem_o_knize" Direction="Out" Type="bool">
					<DesignName StringName="kradez_kn_promluvil_jsem__CIkv" Text="promluvil jsem s pisarem o knize" />
				</Port>
				<Port Name="najdi_doprovod__none" Direction="In" Type="bool">
					<DesignName StringName="kradez_kn_najdi_doprovod__57Ka" Text="Najdi doprovod - none" />
				</Port>
				<Port Name="najdi_knihu" Direction="In" Type="bool">
					<DesignName StringName="kradez_kn_najdi_knihu_SS3a" Text="najdi knihu" />
				</Port>
			</Ports>
			<Definitions>
				<Definition File="kradez_knihy__pisar/pisar__kde_je_kniha.xml" />
			</Definitions>
			<Nodes>
				<State Name="cluesScribe" PositionY="-220" PositionX="-740" RequiredForOutput="trosecko" TypeT="ZjistiVoditkaPisar">
					<Edge From="if8.True" To="SetAbort" />
					<Edge From="if10.True" To="SetPisarNoWeddingWithMiller" />
					<Edge From="if10.False" To="SetPisarAfterMillersWedding" />
					<Edge From="if11.True" To="SetKnihuMaNikvardNoWedding" />
					<Edge From="if11.False" To="SetKnihuMaNikvardWeddingWithMiller" />
					<Edge From="deathtrigger13.OnDeath" To="SetAbort">
						<Vertex>SVQWETKJ</Vertex>
						<Vertex>zyp1QhQn</Vertex>
					</Edge>
				</State>
				<SoulDeathTrigger Name="deathtrigger13" PositionY="480" PositionX="80">
					<Asset Name="Souls" Alias="scribeTrosky" />
					<Edge From="or9.bool" To="IsActive" />
				</SoulDeathTrigger>
				<If Name="if10" PositionY="-80" PositionX="-1050">
					<Edge From="najdi_doprovod__none" To="Condition" />
					<Edge From="svatba_done" To="Exec" />
				</If>
				<If Name="if11" PositionY="110" PositionX="-1050">
					<Edge From="najdi_doprovod__none" To="Condition" />
					<Edge From="pisar__kde_je_kniha.akteri_odhaleni" To="Exec">
						<Vertex>vertex10</Vertex>
						<Vertex>vertex11</Vertex>
						<Vertex>vertex12</Vertex>
					</Edge>
				</If>
				<If Name="if8" PositionY="270" PositionX="-1040">
					<Edge From="hrac_nasel_knihu_exec" To="Exec" />
					<Edge From="or9.bool" To="Condition">
						<Vertex>vertex8</Vertex>
						<Vertex>vertex9</Vertex>
					</Edge>
				</If>
				<zjisti_voditka_ke_knize_u_pisare Name="objectiveVisual2" PositionY="-610" PositionX="-150" RequiredForOutput="trosecko">
					<Edge From="cluesScribe.State" To="Progress" />
				</zjisti_voditka_ke_knize_u_pisare>
				<Function Name="or9" PositionY="-50" PositionX="-110" MethodName="math::boolean::Or" DeclaringType="math::boolean">
					<Edge From="cluesScribe.PisarNoWeddingWithMiller" To="A" />
					<Edge From="cluesScribe.PisarAfterMillersWedding" To="B" />
				</Function>
				<Output Name="Output">
					<Edge From="cluesScribe.OnKnihuMaNikvardWeddingWithMiller" To="akteri_odhaleni">
						<Vertex>vertex3</Vertex>
					</Edge>
					<Edge From="or9.bool" To="itemy_do_inventare">
						<Vertex>vertex7</Vertex>
					</Edge>
					<Edge From="cluesScribe.OnKnihuMaNikvardNoWedding" To="akteri_odhaleni">
						<Vertex>vertex3</Vertex>
					</Edge>
					<Edge From="pisar__kde_je_kniha.lokace_kucharky" To="lokace_kucharky" />
					<Edge From="pisar__kde_je_kniha.lokace_pacholka" To="lokace_pacholka" />
					<Edge From="pisar__kde_je_kniha.lokace_sluzky" To="lokace_sluzky" />
					<Edge From="pisar__kde_je_kniha.misto_nikvardova_posledniho_odpocinku" To="misto_nikvardova_posledniho_odpocinku" />
					<Edge From="pisar__kde_je_kniha.promluvil_jsem_s_pisarem_o_knize" To="promluvil_jsem_s_pisarem_o_knize" />
				</Output>
				<pisar__kde_je_kniha Name="pisar__kde_je_kniha" PositionY="-480" PositionX="140">
					<Edge From="vim_proc_nik_potreboval_lek" To="vim_proc_nik_potreboval_lek">
						<Vertex>vertex13</Vertex>
					</Edge>
					<Edge From="vim_co_se_pise_v_dopise" To="vim_co_se_pise_v_dopise">
						<Vertex>vertex14</Vertex>
					</Edge>
					<Edge From="vim_co_chtel_nik_po_pacholkovi" To="vim_co_chtel_nik_po_pacholkovi">
						<Vertex>vertex15</Vertex>
					</Edge>
					<Edge From="mluvil_jsem_s_kucharkou" To="mluvil_jsem_s_kucharkou">
						<Vertex>vertex16</Vertex>
					</Edge>
					<Edge From="mluvil_jsem_se_sluzkou" To="mluvil_jsem_se_sluzkou">
						<Vertex>vertex17</Vertex>
					</Edge>
					<Edge From="mluvil_jsem_s_pacholkem" To="mluvil_jsem_s_pacholkem">
						<Vertex>vertex18</Vertex>
					</Edge>
					<Edge From="m06_active" To="m06_je_aktivni">
						<Vertex>vertex19</Vertex>
					</Edge>
					<Edge From="or9.bool" To="promluv_si_s_pisarem" />
					<Edge From="najdi_knihu" To="Awake">
						<Vertex>vertex20</Vertex>
					</Edge>
				</pisar__kde_je_kniha>
				<SaveGame Name="savegame12" PositionY="320" PositionX="620">
					<Constant Name="Objective" Value="zjisti_voditka_ke_knize_u_pisare" />
					<Edge From="cluesScribe.OnKnihuMaNikvardWeddingWithMiller" To="EnqueueSave">
						<Vertex>vertex3</Vertex>
					</Edge>
					<Edge From="cluesScribe.OnKnihuMaNikvardNoWedding" To="EnqueueSave">
						<Vertex>vertex3</Vertex>
					</Edge>
				</SaveGame>
			</Nodes>
			<EdgeVertices>
				<EdgeVertex Name="SVQWETKJ" PositionY="700" PositionX="310" />
				<EdgeVertex Name="vertex10" PositionY="-70" PositionX="540" />
				<EdgeVertex Name="vertex11" PositionY="420" PositionX="400" />
				<EdgeVertex Name="vertex12" PositionY="460" PositionX="-1090" />
				<EdgeVertex Name="vertex13" PositionY="-430" PositionX="-1090" />
				<EdgeVertex Name="vertex14" PositionY="-400" PositionX="-1090" />
				<EdgeVertex Name="vertex15" PositionY="-370" PositionX="-1080" />
				<EdgeVertex Name="vertex16" PositionY="-350" PositionX="-1070" />
				<EdgeVertex Name="vertex17" PositionY="-320" PositionX="-1070" />
				<EdgeVertex Name="vertex18" PositionY="-300" PositionX="-1060" />
				<EdgeVertex Name="vertex19" PositionY="-450" PositionX="-1080" />
				<EdgeVertex Name="vertex20" PositionY="-275" PositionX="-1072" />
				<EdgeVertex Name="vertex3" PositionY="270" PositionX="570" />
				<EdgeVertex Name="vertex7" PositionY="240" PositionX="580" />
				<EdgeVertex Name="vertex8" PositionY="460" PositionX="-190" />
				<EdgeVertex Name="vertex9" PositionY="480" PositionX="-960" />
				<EdgeVertex Name="zyp1QhQn" PositionY="700" PositionX="-700" />
			</EdgeVertices>
			<Text StringName="kradez_knihy__pisar_jd3y" Text="Krádež knihy - Písař" />
		</Gameplay>
	</Skald>
</Database>