<?xml version="1.0" encoding="utf-8"?>
<Database xmlns:xsd="http://www.w3.org/2001/XMLSchema" xmlns:xsi="http://www.w3.org/2001/XMLSchema-instance" Name="brambora">
	<Skald>
		<Dialog Name="bark__objeveni_masoveho_hrobu">
			<Text StringName="bark__objeveni_masoveho_h_QXTa" Text="bark - objevení masového hrobu" />
			<Dialogue Type="ingame monolog" TechnicalStatus="Enabled" DefaultMaxDistance="10" Initiator="NonPlayer" GesturesNotNeeded="true">
				<Decision Name="dec1" Priority="SideQuestAdditionals" Alias="stareKosti_barkObjeveniMasovehoHrobu">
					<Sequences>
						<Sequence EndType="EndDialogue" Name="seq1">
							<DesignName StringName="bark__obj_seq1_8E1d" Text="seq1" />
							<Elements>
								<Response Role="HENRY">
									<Parenthetical>
										<Text StringName="bark_henry_pro_sbe_i1SM" Text="pro sbe" />
									</Parenthetical>
									<Text StringName="bark_henry_proboha_tolik__yMcH" Text="Tohle vypadá na ten hromadnej hrob hostů z kutnohorský hostiny, o kterým jsem četl..." />
								</Response>
								<Response Role="HENRY">
									<Text StringName="bark_henry_co_se_tady_sta_ys6c" Text="Nepsalo se v tý knížce, že je pohřbili se všema cennostma?" />
									<ReviewNotesConcept>
										<Item Date="2020-04-23 12:24:59" UserName="martin.sourek" Text="tady bych se nejspíš nebál odkázat na morticia, nebo kdo na to bude mít odpověď." AcceptState="Accepted" />
									</ReviewNotesConcept>
								</Response>
							</Elements>
						</Sequence>
					</Sequences>
				</Decision>
			</Dialogue>
		</Dialog>
	</Skald>
</Database>