<?xml version="1.0" encoding="utf-8"?>
<Database xmlns:xsd="http://www.w3.org/2001/XMLSchema" xmlns:xsi="http://www.w3.org/2001/XMLSchema-instance" Name="brambora">
	<Skald>
		<Module Name="tour_barks">
			<Definitions>
				<Definition File="tour_barks/hrac_se_vzdalil.xml" />
				<Definition File="tour_barks/hrac_se_vratil.xml" />
				<Definition File="tour_barks/hrac_se_blizi_k_failu_nasledovani.xml" />
			</Definitions>
			<Nodes>
				<hrac_se_blizi_k_failu_nasledovani Name="hrac_se_blizi_k_failu_nasledovani" PositionY="290" PositionX="-100" />
				<hrac_se_vratil Name="hrac_se_vratil" PositionY="80" PositionX="-100" />
				<hrac_se_vzdalil Name="hrac_se_vzdalil" PositionY="-100" PositionX="-100" />
			</Nodes>
			<Text StringName="tour_barks_f4wO" Text="Tour barks" />
		</Module>
	</Skald>
</Database>