<?xml version="1.0" encoding="utf-8"?>
<Database xmlns:xsd="http://www.w3.org/2001/XMLSchema" xmlns:xsi="http://www.w3.org/2001/XMLSchema-instance" Name="brambora">
	<Skald>
		<Dialog Name="utok_na_malesov__utocnik_barkuje_na_nepritele_">
			<Text StringName="utok_na_malesov__utocnik__161Q" Text="Útok na Malešov - útočník bárkuje na nepřítele " />
			<Elements>
				<GameplayActionElement>
					<Text StringName="utok_na_m_barky_na_zacate_kZpx" Text="Bárky na začátek boje o předhradí a potom i o vnitřní hrad." />
				</GameplayActionElement>
			</Elements>
			<Dialogue Type="ingame monolog" TechnicalStatus="Enabled" Hearing="50" Initiator="NonPlayer">
				<Decision Name="dec1" Priority="MainQuestSubmission" Alias="utokNaMalesov_utokNaMalesovUtocnikBarkujeNaNepritele">
					<Sequences>
						<Sequence EndType="Decision" Name="seq1">
							<DesignName StringName="utok_na_m_seq1_kI8a" Text="seq1" />
							<Elements>
								<Response Role="UTOK_NA_MALESOV_UTOCNIK_BARKUJE_NA_NEPRITELE" />
							</Elements>
							<Decision Name="dec2" Priority="MainQuestSubmission" DesignName="pool NPC bárkuje na nepřítele" Autoselect="true" VoiceoverReductionMaxSequences="2" VoiceoverReductionRole="UTOK_NA_MALESOV_UTOCNIK_BARKUJE_NA_NEPRITELE">
								<Sequences>
									<Sequence EndType="EndDialogue" Cooldown="2m" Name="seq2">
										<DesignName StringName="utok_na_m_seq2_r6U4" Text="seq2" />
										<Elements>
											<Response Role="UTOK_NA_MALESOV_UTOCNIK_BARKUJE_NA_NEPRITELE">
												<Parenthetical>
													<Text StringName="utok_utok_na_m_v_boji_kri_Rp52" Text="v boji, křičí" />
												</Parenthetical>
												<Text StringName="utok_utok_na_m_hrr_na_ne_KmBE" Text="Hrr na ně!" />
											</Response>
										</Elements>
									</Sequence>
									<Sequence EndType="EndDialogue" Cooldown="2m" Name="seq3">
										<DesignName StringName="utok_na_m_seq3_bSCz" Text="seq3" />
										<Elements>
											<Response Role="UTOK_NA_MALESOV_UTOCNIK_BARKUJE_NA_NEPRITELE">
												<Parenthetical>
													<Text StringName="utok_utok_na_m_v_boji_kri_9SPi" Text="v boji, křičí" />
												</Parenthetical>
												<Text StringName="utok_utok_na_m_bijte_ty_k_qGwL" Text="Bijte ty kurvy!" />
											</Response>
										</Elements>
									</Sequence>
									<Sequence EndType="EndDialogue" Cooldown="2m" Name="seq4">
										<DesignName StringName="utok_na_m_seq4_Zgra" Text="seq4" />
										<Elements>
											<Response Role="UTOK_NA_MALESOV_UTOCNIK_BARKUJE_NA_NEPRITELE">
												<Parenthetical>
													<Text StringName="utok_utok_na_m_v_boji_kri_Q4bm" Text="v boji, křičí" />
												</Parenthetical>
												<Text StringName="utok_utok_na_m_bijte_je_FpsQ" Text="Bijte je!" />
											</Response>
										</Elements>
									</Sequence>
									<Sequence EndType="EndDialogue" Cooldown="2m" Name="seq5">
										<DesignName StringName="utok_na_m_seq5_xYb8" Text="seq5" />
										<Elements>
											<Response Role="UTOK_NA_MALESOV_UTOCNIK_BARKUJE_NA_NEPRITELE">
												<Parenthetical>
													<Text StringName="utok_utok_na_m_v_boji_kri_8LSQ" Text="v boji, křičí" />
												</Parenthetical>
												<Text StringName="utok_utok_na_m_na_ne_S49m" Text="Na ně!" />
											</Response>
										</Elements>
									</Sequence>
									<Sequence EndType="EndDialogue" Cooldown="2m" Name="seq6">
										<DesignName StringName="utok_na_m_seq6_Zp08" Text="seq6" />
										<Elements>
											<Response Role="UTOK_NA_MALESOV_UTOCNIK_BARKUJE_NA_NEPRITELE">
												<Parenthetical>
													<Text StringName="utok_utok_na_m_v_boji_kri_KwbM" Text="v boji, křičí" />
												</Parenthetical>
												<Text StringName="utok_utok_na_m_hovada_zhe_jhvT" Text="Hovada! Zhebněte!" />
											</Response>
										</Elements>
									</Sequence>
									<Sequence EndType="EndDialogue" Cooldown="2m" Name="seq7">
										<DesignName StringName="utok_na_m_seq7_fhiN" Text="seq7" />
										<Elements>
											<Response Role="UTOK_NA_MALESOV_UTOCNIK_BARKUJE_NA_NEPRITELE">
												<Parenthetical>
													<Text StringName="utok_utok_na_m_v_boji_kri_CRQU" Text="v boji, křičí" />
												</Parenthetical>
												<Text StringName="utok_utok_na_m_parchanti__Qwx2" Text="Parchanti! Chcípněte!" />
											</Response>
										</Elements>
									</Sequence>
									<Sequence EndType="EndDialogue" Cooldown="2m" Name="seq8">
										<DesignName StringName="utok_na_m_seq8_Tw60" Text="seq8" />
										<Elements>
											<Response Role="UTOK_NA_MALESOV_UTOCNIK_BARKUJE_NA_NEPRITELE">
												<Parenthetical>
													<Text StringName="utok_utok_na_m_v_boji_kri_qRy1" Text="v boji křičí" />
												</Parenthetical>
												<Text StringName="utok_utok_na_m_svine_dost_kPef" Text="Svině! Dostanete do držky!" />
											</Response>
										</Elements>
									</Sequence>
									<Sequence EndType="EndDialogue" Cooldown="2m" Name="seq9">
										<DesignName StringName="utok_na_m_seq9_Tsxl" Text="seq9" />
										<Elements>
											<Response Role="UTOK_NA_MALESOV_UTOCNIK_BARKUJE_NA_NEPRITELE">
												<Parenthetical>
													<Text StringName="utok_utok_na_m_v_boji_kri_peI1" Text="v boji křičí" />
												</Parenthetical>
												<Text StringName="utok_utok_na_m_do_nich_mr_vTWG" Text="Do nich! Mrdejte je do hlav!" />
											</Response>
										</Elements>
									</Sequence>
									<Sequence EndType="EndDialogue" VoiceCategory="german" Cooldown="2m" Name="german01">
										<DesignName StringName="utok_na_m_german01_W4dJ" Text="german01" />
										<Elements>
											<Response Role="UTOK_NA_MALESOV_UTOCNIK_BARKUJE_NA_NEPRITELE">
												<Parenthetical>
													<Text StringName="utok_utok_na_m_v_boji_kri_BRSa" Text="v boji křičí" />
												</Parenthetical>
												<Text StringName="utok_utok_na_m_schweinehu_I9rj" Text="Schweinehunde! Stirb! Stirb!" />
											</Response>
										</Elements>
									</Sequence>
									<Sequence EndType="EndDialogue" VoiceCategory="german" Cooldown="2m" Name="german02">
										<DesignName StringName="utok_na_m_german02_dZhy" Text="german02" />
										<Elements>
											<Response Role="UTOK_NA_MALESOV_UTOCNIK_BARKUJE_NA_NEPRITELE">
												<Parenthetical>
													<Text StringName="utok_utok_na_m_v_boji_kri_8S8t" Text="v boji křičí" />
												</Parenthetical>
												<Text StringName="utok_utok_na_m_schlag_das_LWWq" Text="Schlag das Blut!" />
											</Response>
										</Elements>
									</Sequence>
									<Sequence EndType="EndDialogue" VoiceCategory="german" Cooldown="2m" Name="german03">
										<DesignName StringName="utok_na_m_german03_gzYH" Text="german03" />
										<Elements>
											<Response Role="UTOK_NA_MALESOV_UTOCNIK_BARKUJE_NA_NEPRITELE">
												<Parenthetical>
													<Text StringName="utok_utok_na_m_v_boji_kri_rg2V" Text="v boji křičí" />
												</Parenthetical>
												<Text StringName="utok_utok_na_m_los_gehts__1rsb" Text="Los geht's! Blut! Blut!" />
											</Response>
										</Elements>
									</Sequence>
									<Sequence EndType="EndDialogue" Cooldown="2m" Name="seq13">
										<DesignName StringName="utok_na_m_seq13_Ajzm" Text="seq13" />
										<Elements>
											<Response Role="UTOK_NA_MALESOV_UTOCNIK_BARKUJE_NA_NEPRITELE">
												<Parenthetical>
													<Text StringName="utok_utok_na_m_v_boji_kri_32za" Text="v boji křičí" />
												</Parenthetical>
												<Text StringName="utok_utok_na_m_do_nich_kr_mnhq" Text="Do nich! Kreéév!" />
											</Response>
										</Elements>
									</Sequence>
								</Sequences>
							</Decision>
						</Sequence>
					</Sequences>
				</Decision>
			</Dialogue>
		</Dialog>
	</Skald>
</Database>