<?xml version="1.0" encoding="utf-8"?>
<Database xmlns:xsd="http://www.w3.org/2001/XMLSchema" xmlns:xsi="http://www.w3.org/2001/XMLSchema-instance" Name="brambora">
	<Skald>
		<DialogWrapper Name="doneses_kosti_opatovi_kdyz_si_mu_lhal">
			<Ports>
				<Port Name="odevzdani_vsech_kosti" Direction="Out" Type="trigger">
					<DesignName StringName="doneses_k_odevzdani_vsech_bByg" Text="odevzdání všech kostí" />
				</Port>
				<Port Name="available_dialog" Direction="In" Type="bool">
					<DesignName StringName="doneses_k_available_dialog_lhmg" Text="available dialog" />
				</Port>
				<Port Name="fail_opatem" Direction="In" Type="bool">
					<DesignName StringName="doneses_k_fail_opatem_JQG5" Text="Fail Opatem" />
				</Port>
			</Ports>
			<Definitions>
				<Definition File="doneses_kosti_opatovi_kdyz_si_mu_lhal/doneses_kosti_opatovi_kdyz_si_mu_lhal.xml" />
			</Definitions>
			<Nodes>
				<doneses_kosti_opatovi_kdyz_si_mu_lhal Name="doneses_kosti_opatovi_kdyz_si_mu_lhal">
					<Edge From="available_dialog" To="available_dialog" />
					<Edge From="mamkosti.mam_vsechny_kosti" To="mam_vsechny_kosti" />
					<Edge From="fail_opatem" To="fail_opatem" />
				</doneses_kosti_opatovi_kdyz_si_mu_lhal>
				<mamkosti Name="mamkosti" PositionY="-170" PositionX="-250" Namespace="drak" />
				<Output Name="Output">
					<Edge From="doneses_kosti_opatovi_kdyz_si_mu_lhal.odevzdani_vsech_kosti" To="odevzdani_vsech_kosti" />
				</Output>
			</Nodes>
		</DialogWrapper>
	</Skald>
</Database>