<?xml version="1.0" encoding="utf-8"?>
<Database xmlns:xsd="http://www.w3.org/2001/XMLSchema" xmlns:xsi="http://www.w3.org/2001/XMLSchema-instance" Name="brambora">
	<Skald>
		<Dialog Name="baba_reakce_na_zabijeni_zvirat">
			<Text StringName="baba_reakce_na_zabijeni_z_v9Dh" Text="Baba reakce na zabijeni zvirat" />
			<Dialogue Type="ingame monolog" TechnicalStatus="Enabled" Initiator="NonPlayer" ClashPriority="Flavor" GesturesSetDate="2024-01-09T12:21:06.6746511+01:00" GesturesSetResponseCount="3">
				<SelectedSouls>
					<SelectedSoul Role="BOZENA_KORENARKA" Voice="zenaHodneStara" Type="Wave" Language="ENG" />
				</SelectedSouls>
				<Decision Name="dec1" Priority="MainQuestSubmission" Alias="zachrana_babaReakceNaZabijeniZviratPlaceholder">
					<Sequences>
						<Sequence EndType="EndDialogue" Name="seq1">
							<DesignName StringName="baba_reak_seq1_gLOh" Text="seq1" />
							<Elements>
								<Response Role="BOZENA_KORENARKA" ReferenceLength="3.04">
									<Parenthetical>
										<Text StringName="baba_bozena_ko_prekvapene_Nx6a" Text="překvapeně, soucitně" />
									</Parenthetical>
									<Text StringName="baba_bozena_ko_ty_ses_ale_QDpI" Text="Kristovy rány, nebohý zvíře!" />
									<Commands>
										<FacialMoodCommand FacialMood="angry2" />
										<AnimationCommand Delay="0.04" FragmentId="ADLG_Cross" Guid="360e59b6-f7d4-8d55-add0-88d23acc0e26" Variant="0" />
										<AnimationCommand Delay="3.03" FragmentId="ADLG_Confusion" Guid="d66ec093-3ef1-4d8c-b717-68254998806c" Variant="5" />
									</Commands>
								</Response>
								<Response Role="BOZENA_KORENARKA" ReferenceLength="3.46">
									<Parenthetical>
										<Text StringName="baba_bozena_ko_podrazdene_it98" Text="podrážděně, vyčítavě" />
									</Parenthetical>
									<Text StringName="baba_bozena_ko_pominul_se_k5d2" Text="Pominul ses nebo co to do tebe vjelo?!" />
									<Commands>
										<AnimationCommand Delay="1.94" FragmentId="ADLG_Frustration" Guid="559c4856-a553-47f4-a7ce-cce43e70613d" Variant="0" />
									</Commands>
								</Response>
								<Response Role="BOZENA_KORENARKA" StartDelay="0.27" ReferenceLength="5.29">
									<Parenthetical>
										<Text StringName="baba_bozena_ko_nesouhlane_xM91" Text="nesouhlaně, výstražně" />
									</Parenthetical>
									<Text StringName="baba_bozena_ko_udelat_toh_hmf1" Text="Udělat tohle v Troskovicích, rychtář tě bez vokolků ztříská, ty ničemníku." />
									<Commands>
										<MoodCommand Delay="0.35" Mood="angry" />
									</Commands>
								</Response>
							</Elements>
						</Sequence>
					</Sequences>
				</Decision>
			</Dialogue>
		</Dialog>
	</Skald>
</Database>