<?xml version="1.0" encoding="utf-8"?>
<Database xmlns:xsd="http://www.w3.org/2001/XMLSchema" xmlns:xsi="http://www.w3.org/2001/XMLSchema-instance" Name="brambora">
	<Skald>
		<FaderDialog Name="svepomoc__hrac_se_vzdava_muzi">
			<Text StringName="svepomoc__hrac_se_vzdava__9A3m" Text="Svépomoc - hráč se vzdává muži" />
			<Dialogue TechnicalStatus="Enabled" AllowFarewell="false" AllowGreeting="false" Initiator="NonPlayer" GesturesSetDate="2024-05-22T14:09:16.4715484+02:00" GesturesSetResponseCount="5">
				<SelectedSouls>
					<SelectedSoul Role="SVEPOMOC_MUZ_INCLUDE" Voice="fejk" Type="Computed" />
					<SelectedSoul Role="HRAC" Voice="tomMcKay" Type="Wave" Language="ENG" />
				</SelectedSouls>
				<Decision Name="dec1" Alias="svepomoc_svepomocHracSeVzdavaMuzi" Included="true">
					<Sequences>
						<Sequence EndType="Decision" Name="seq1">
							<DesignName StringName="svepomoc__seq1_oIXU" Text="seq1" />
							<Elements>
								<Response Role="SVEPOMOC_MUZ_INCLUDE" />
							</Elements>
							<Decision Name="dec2" Autoselect="true">
								<Sequences>
									<Sequence EndType="EndDialogue" Cooldown="32s" Name="seq20">
										<DesignName StringName="svepomoc__seq20_p7CO" Text="seq20" />
										<Elements>
											<Response Role="HRAC" ReferenceLength="1.69">
												<Text StringName="svep_hrac_promin_domluvim_gDxq" Text="Promiň, domluvíme se." />
												<Commands>
													<FacialMoodCommand FacialMood="nervous1" />
													<AnimationCommand Delay="0" FragmentId="ADLG_Easy_man" Guid="a88b0649-f2db-45b9-ac75-fbe939616780" Variant="0" />
													<CameraCommand CameraType="CloseShot" />
												</Commands>
											</Response>
										</Elements>
									</Sequence>
									<Sequence EndType="EndDialogue" Cooldown="32s" Name="seq19">
										<DesignName StringName="svepomoc__seq19_d571" Text="seq19" />
										<Elements>
											<Response Role="HRAC" ReferenceLength="1.59">
												<Text StringName="svep_hrac_nejak_se_urcite_3FbW" Text="Nějak se určitě domluvíme." />
												<Commands>
													<FacialMoodCommand FacialMood="nervous1" />
													<AnimationCommand Delay="0.02" FragmentId="ADLG_Gesture" Guid="5bfd99ad-b27c-429d-bf26-d9ae6bf0b730" Variant="8" />
													<CameraCommand CameraType="CloseShot" />
												</Commands>
											</Response>
										</Elements>
									</Sequence>
									<Sequence EndType="EndDialogue" Cooldown="32s" Name="seq18">
										<DesignName StringName="svepomoc__seq18_RBI3" Text="seq18" />
										<Elements>
											<Response Role="HRAC" ReferenceLength="3.08">
												<Text StringName="svep_hrac_v_klidu_promluv_fjmk" Text="V klidu, promluvme si o tom." />
												<Commands>
													<FacialMoodCommand FacialMood="happy1" />
													<AnimationCommand Delay="0" FragmentId="ADLG_Nod" Guid="2ddda320-2a14-4160-b352-ad7c194f57b3" Variant="0" />
													<CameraCommand CameraType="CloseShot" />
												</Commands>
											</Response>
										</Elements>
									</Sequence>
									<Sequence EndType="EndDialogue" Cooldown="32s" Name="seq17">
										<DesignName StringName="svepomoc__seq17_26GA" Text="seq17" />
										<Elements>
											<Response Role="HRAC" ReferenceLength="1.15">
												<Text StringName="svep_hrac_vyresime_to_spo_5XWY" Text="Vyřešíme to spolu." />
												<Commands>
													<FacialMoodCommand FacialMood="thinking1" />
													<AnimationCommand Delay="0" FragmentId="ADLG_Nod" Guid="e42b3bf3-fd0e-478c-b9f7-cacc887c47b9" Variant="3" />
													<CameraCommand CameraType="CloseShot" />
												</Commands>
											</Response>
										</Elements>
									</Sequence>
									<Sequence EndType="EndDialogue" Cooldown="32s" Name="seq16">
										<DesignName StringName="svepomoc__seq16_Iu3q" Text="seq16" />
										<Elements>
											<Response Role="HRAC" ReferenceLength="2.38">
												<Text StringName="svep_hrac_pockej_domluvim_vUx8" Text="Počkej, domluvíme se." />
												<Commands>
													<FacialMoodCommand FacialMood="angry1" />
													<AnimationCommand Delay="0" FragmentId="ADLG_Easy_man" Guid="a88b0649-f2db-45b9-ac75-fbe939616780" Variant="0" />
													<CameraCommand CameraType="CloseShot" />
												</Commands>
											</Response>
										</Elements>
									</Sequence>
								</Sequences>
							</Decision>
						</Sequence>
					</Sequences>
				</Decision>
			</Dialogue>
		</FaderDialog>
	</Skald>
</Database>